flagger/__init__.py
flagger/flagger-386.dll
flagger/flagger-amd64.dll
flagger/flagger.py
flagger/libflagger-386.so
flagger/libflagger-amd64.so
flagger/libflagger.dylib
flagger/version.py
flagger-3.1.0.dist-info/LICENSE
flagger-3.1.0.dist-info/METADATA
flagger-3.1.0.dist-info/WHEEL
flagger-3.1.0.dist-info/top_level.txt
flagger-3.1.0.dist-info/RECORD
